rbln_replayPulse/main.py
rbln_replayPulse/player.py
rbln_replayPulse/recorder.py
rbln_replayPulse/settings.py
rbln_replaypulse-2.0.0.dist-info/METADATA
rbln_replaypulse-2.0.0.dist-info/WHEEL
rbln_replaypulse-2.0.0.dist-info/entry_points.txt
rbln_replaypulse-2.0.0.dist-info/top_level.txt
rbln_replaypulse-2.0.0.dist-info/RECORD
