Metadata-Version: 2.1
Name: rbln-replaypulse
Version: 2.0.0
Summary: RBLN-replayPulse
Home-page: UNKNOWN
Author: JunHui Ahn
Author-email: june3780@rebellions.ai
License: UNKNOWN
Platform: UNKNOWN
Requires-Python: >=3
Requires-Dist: matplotlib
Requires-Dist: pandas
Requires-Dist: pytz
